dynsys/__init__.py
dynsys/app.py
dynsys/core.py
dynsys/equation.py
dynsys/grid.py
dynsys/lyapunov.py
dynsys/phase.py
dynsys/cl/__init__.py
dynsys/cl/attractors/kernels.cl
dynsys/cl/attractors/rotations.clh
dynsys/cl/common/bsearch.clh
dynsys/cl/common/colors.clh
dynsys/cl/common/complex.clh
dynsys/cl/common/grid.clh
dynsys/cl/common/hash.clh
dynsys/cl/common/integrate.clh
dynsys/cl/common/iterate.clh
dynsys/cl/common/point.clh
dynsys/cl/common/random.clh
dynsys/cl/common/types.clh
dynsys/cl/common/util.clh
dynsys/cl/fbc/kernels.cl
dynsys/cl/lyapunov/kernels.cl
dynsys/cl/parameter_map/kernels.cl
dynsys/cl/phase/kernels.cl
dynsys/cl/tree/kernels.cl
dynsys-0.0.0.1.dist-info/METADATA
dynsys-0.0.0.1.dist-info/WHEEL
dynsys-0.0.0.1.dist-info/top_level.txt
dynsys-0.0.0.1.dist-info/RECORD
