Metadata-Version: 2.1
Name: dynsys
Version: 0.0.0.1
Summary: UNKNOWN
Home-page: https://github.com/modelflat/dynsys
Author: modelflat
License: UNKNOWN
Project-URL: Issues, https://github.com/modelflat/dynsys/issues
Keywords: opencl research nonlinear dynamical-systems
Platform: UNKNOWN
Classifier: Development Status :: 2 - Pre-Alpha
Classifier: Programming Language :: Python :: 3
Requires-Python: >=3
Requires-Dist: pyopencl
Requires-Dist: PyQt5
Requires-Dist: PySide2
